plex_sync/__init__.py
plex_sync/sync.py
plex_sync/version.py
plex_sync-0.0.3.dist-info/DESCRIPTION.rst
plex_sync-0.0.3.dist-info/METADATA
plex_sync-0.0.3.dist-info/RECORD
plex_sync-0.0.3.dist-info/WHEEL
plex_sync-0.0.3.dist-info/entry_points.txt
plex_sync-0.0.3.dist-info/metadata.json
plex_sync-0.0.3.dist-info/top_level.txt
plexapi/__init__.py
plexapi/alert.py
plexapi/audio.py
plexapi/base.py
plexapi/client.py
plexapi/compat.py
plexapi/config.py
plexapi/exceptions.py
plexapi/library.py
plexapi/media.py
plexapi/myplex.py
plexapi/photo.py
plexapi/playlist.py
plexapi/playqueue.py
plexapi/server.py
plexapi/settings.py
plexapi/sync.py
plexapi/utils.py
plexapi/video.py
