Metadata-Version: 2.0
Name: plex-sync
Version: 0.0.3
Summary: Sync playback status between Plex servers
Home-page: https://github.com/d1vanloon/python-plex-sync
Author: David Van Loon
Author-email: david+pypi@davidvanloon.me
License: MIT
Requires-Dist: requests
Requires-Dist: tqdm
Requires-Dist: websocket-client
